zerovox/__init__.py
zerovox/demo.py
zerovox/parallel_wavegan/__init__.py
zerovox/parallel_wavegan/bin/__init__.py
zerovox/parallel_wavegan/bin/compute_statistics.py
zerovox/parallel_wavegan/bin/decode.py
zerovox/parallel_wavegan/bin/evaluate_f0.py
zerovox/parallel_wavegan/bin/evaluate_mcd.py
zerovox/parallel_wavegan/bin/normalize.py
zerovox/parallel_wavegan/bin/preprocess.py
zerovox/parallel_wavegan/bin/train.py
zerovox/parallel_wavegan/datasets/__init__.py
zerovox/parallel_wavegan/datasets/audio_mel_dataset.py
zerovox/parallel_wavegan/datasets/scp_dataset.py
zerovox/parallel_wavegan/distributed/__init__.py
zerovox/parallel_wavegan/distributed/launch.py
zerovox/parallel_wavegan/functions/__init__.py
zerovox/parallel_wavegan/functions/vector_quantizer.py
zerovox/parallel_wavegan/layers/__init__.py
zerovox/parallel_wavegan/layers/causal_conv.py
zerovox/parallel_wavegan/layers/duration_predictor.py
zerovox/parallel_wavegan/layers/layer_norm.py
zerovox/parallel_wavegan/layers/length_regulator.py
zerovox/parallel_wavegan/layers/pqmf.py
zerovox/parallel_wavegan/layers/residual_block.py
zerovox/parallel_wavegan/layers/residual_stack.py
zerovox/parallel_wavegan/layers/sine.py
zerovox/parallel_wavegan/layers/tade_res_block.py
zerovox/parallel_wavegan/layers/tf_layers.py
zerovox/parallel_wavegan/layers/upsample.py
zerovox/parallel_wavegan/layers/variance_predictor.py
zerovox/parallel_wavegan/layers/vector_quantize_codebook.py
zerovox/parallel_wavegan/losses/__init__.py
zerovox/parallel_wavegan/losses/adversarial_loss.py
zerovox/parallel_wavegan/losses/duration_prediction_loss.py
zerovox/parallel_wavegan/losses/feat_match_loss.py
zerovox/parallel_wavegan/losses/mel_loss.py
zerovox/parallel_wavegan/losses/stft_loss.py
zerovox/parallel_wavegan/models/__init__.py
zerovox/parallel_wavegan/models/hifigan.py
zerovox/parallel_wavegan/models/melgan.py
zerovox/parallel_wavegan/models/parallel_wavegan.py
zerovox/parallel_wavegan/models/style_melgan.py
zerovox-0.3.3.dist-info/licenses/LICENSE
zerovox-0.3.3.dist-info/METADATA
zerovox-0.3.3.dist-info/WHEEL
zerovox-0.3.3.dist-info/entry_points.txt
zerovox-0.3.3.dist-info/top_level.txt
zerovox-0.3.3.dist-info/RECORD
