Metadata-Version: 2.4
Name: zerovox
Version: 0.3.3
Summary: zero-shot realtime TTS system, fully offline, free and open source
Home-page: https://github.com/gooofy/zerovox
Download-URL: https://github.com/gooofy/zerovox/archive/0.3.1.tar.gz
Author: Günter Bartsch
Author-email: Günter Bartsch <guenter@zamia.org>
Maintainer-email: Günter Bartsch <guenter@zamia.org>
License:                                  Apache License
Project-URL: Homepage, https://github.com/gooofy/zerovox
Project-URL: Repository, https://github.com/gooofy/zerovox.git
Project-URL: Bug Tracker, https://github.com/gooofy/zerovox/issues
Keywords: text-to-speech,deep-learning,speech,pytorch,tts,speech-synthesis,voice-synthesis,voice-cloning,speaker-encodings,melgan,speaker-encoder,multi-speaker-tts,hifigan,tts-model
Classifier: Development Status :: 4 - Beta
Classifier: Environment :: Console
Classifier: Intended Audience :: Developers
Classifier: License :: OSI Approved :: Apache Software License
Classifier: Natural Language :: English
Classifier: Natural Language :: German
Classifier: Operating System :: POSIX :: Linux
Classifier: Programming Language :: Python
Classifier: Topic :: Multimedia :: Sound/Audio :: Speech
Classifier: Topic :: Multimedia :: Sound/Audio :: Sound Synthesis
Classifier: Topic :: Scientific/Engineering :: Artificial Intelligence
Requires-Python: >=3.10
License-File: LICENSE
Requires-Dist: torch>=2.5.0
Requires-Dist: torchinfo>=1.8.0
Requires-Dist: torchaudio>=2.5.1
Requires-Dist: nltk>=3.8.1
Requires-Dist: num2words>=0.5.13
Requires-Dist: readline>=6.2.4.1
Requires-Dist: librosa>=0.10.2
Requires-Dist: lightning>=2.4.0
Requires-Dist: einops>=0.8.0
Requires-Dist: sounddevice>=0.4.7
Requires-Dist: setproctitle>=1.3.3
Requires-Dist: psutil>=6.0.0
Requires-Dist: h5py>=3.11.0
Requires-Dist: uroman>=1.3.1
Requires-Dist: nemo_text_processing>=1.1.0
Dynamic: author
Dynamic: download-url
Dynamic: home-page
Dynamic: license-file
